{
  "id": "c1ecff84-7d08-404b-9485-2298b6d3d8fa",
  "prevId": "d2f147d4-ac0e-4cc5-ba4f-95b506374038",
  "version": "7",
  "dialect": "postgresql",
  "tables": {
    "public.accounts": {
      "name": "accounts",
      "schema": "",
      "columns": {
        "id": {
          "name": "id",
          "type": "serial",
          "primaryKey": true,
          "notNull": true
        },
        "user_id": {
          "name": "user_id",
          "type": "integer",
          "primaryKey": false,
          "notNull": false
        },
        "auth0_sub": {
          "name": "auth0_sub",
          "type": "varchar(255)",
          "primaryKey": false,
          "notNull": true
        },
        "name": {
          "name": "name",
          "type": "varchar(100)",
          "primaryKey": false,
          "notNull": false
        },
        "nickname": {
          "name": "nickname",
          "type": "varchar(100)",
          "primaryKey": false,
          "notNull": false
        },
        "email": {
          "name": "email",
          "type": "varchar(255)",
          "primaryKey": false,
          "notNull": false
        },
        "email_verified": {
          "name": "email_verified",
          "type": "boolean",
          "primaryKey": false,
          "notNull": false,
          "default": false
        },
        "picture": {
          "name": "picture",
          "type": "varchar(1000)",
          "primaryKey": false,
          "notNull": false
        },
        "app_id": {
          "name": "app_id",
          "type": "integer",
          "primaryKey": false,
          "notNull": false
        },
        "created_at": {
          "name": "created_at",
          "type": "timestamp",
          "primaryKey": false,
          "notNull": false,
          "default": "now()"
        },
        "updated_at": {
          "name": "updated_at",
          "type": "timestamp",
          "primaryKey": false,
          "notNull": false,
          "default": "now()"
        }
      },
      "indexes": {},
      "foreignKeys": {
        "accounts_user_id_users_id_fk": {
          "name": "accounts_user_id_users_id_fk",
          "tableFrom": "accounts",
          "tableTo": "users",
          "columnsFrom": [
            "user_id"
          ],
          "columnsTo": [
            "id"
          ],
          "onDelete": "no action",
          "onUpdate": "no action"
        },
        "accounts_app_id_applications_id_fk": {
          "name": "accounts_app_id_applications_id_fk",
          "tableFrom": "accounts",
          "tableTo": "applications",
          "columnsFrom": [
            "app_id"
          ],
          "columnsTo": [
            "id"
          ],
          "onDelete": "no action",
          "onUpdate": "no action"
        }
      },
      "compositePrimaryKeys": {},
      "uniqueConstraints": {
        "accounts_auth0_sub_unique": {
          "name": "accounts_auth0_sub_unique",
          "nullsNotDistinct": false,
          "columns": [
            "auth0_sub"
          ]
        }
      },
      "policies": {},
      "checkConstraints": {},
      "isRLSEnabled": false
    },
    "public.applications": {
      "name": "applications",
      "schema": "",
      "columns": {
        "id": {
          "name": "id",
          "type": "serial",
          "primaryKey": true,
          "notNull": true
        },
        "app_name": {
          "name": "app_name",
          "type": "varchar(100)",
          "primaryKey": false,
          "notNull": true
        },
        "domain": {
          "name": "domain",
          "type": "varchar(255)",
          "primaryKey": false,
          "notNull": true
        },
        "created_at": {
          "name": "created_at",
          "type": "integer",
          "primaryKey": false,
          "notNull": true,
          "default": "EXTRACT(EPOCH FROM CURRENT_TIMESTAMP)"
        },
        "updated_at": {
          "name": "updated_at",
          "type": "integer",
          "primaryKey": false,
          "notNull": true,
          "default": "EXTRACT(EPOCH FROM CURRENT_TIMESTAMP)"
        }
      },
      "indexes": {},
      "foreignKeys": {},
      "compositePrimaryKeys": {},
      "uniqueConstraints": {},
      "policies": {},
      "checkConstraints": {},
      "isRLSEnabled": false
    },
    "public.device_accounts": {
      "name": "device_accounts",
      "schema": "",
      "columns": {
        "account_id": {
          "name": "account_id",
          "type": "integer",
          "primaryKey": false,
          "notNull": true
        },
        "device_id": {
          "name": "device_id",
          "type": "integer",
          "primaryKey": false,
          "notNull": true
        },
        "is_active": {
          "name": "is_active",
          "type": "boolean",
          "primaryKey": false,
          "notNull": false,
          "default": true
        },
        "last_login": {
          "name": "last_login",
          "type": "timestamp",
          "primaryKey": false,
          "notNull": false,
          "default": "now()"
        },
        "created_at": {
          "name": "created_at",
          "type": "timestamp",
          "primaryKey": false,
          "notNull": false,
          "default": "now()"
        },
        "updated_at": {
          "name": "updated_at",
          "type": "timestamp",
          "primaryKey": false,
          "notNull": false,
          "default": "now()"
        }
      },
      "indexes": {},
      "foreignKeys": {
        "device_accounts_account_id_accounts_id_fk": {
          "name": "device_accounts_account_id_accounts_id_fk",
          "tableFrom": "device_accounts",
          "tableTo": "accounts",
          "columnsFrom": [
            "account_id"
          ],
          "columnsTo": [
            "id"
          ],
          "onDelete": "no action",
          "onUpdate": "no action"
        },
        "device_accounts_device_id_devices_id_fk": {
          "name": "device_accounts_device_id_devices_id_fk",
          "tableFrom": "device_accounts",
          "tableTo": "devices",
          "columnsFrom": [
            "device_id"
          ],
          "columnsTo": [
            "id"
          ],
          "onDelete": "no action",
          "onUpdate": "no action"
        }
      },
      "compositePrimaryKeys": {
        "device_accounts_account_id_device_id_pk": {
          "name": "device_accounts_account_id_device_id_pk",
          "columns": [
            "account_id",
            "device_id"
          ]
        }
      },
      "uniqueConstraints": {},
      "policies": {},
      "checkConstraints": {},
      "isRLSEnabled": false
    },
    "public.devices": {
      "name": "devices",
      "schema": "",
      "columns": {
        "id": {
          "name": "id",
          "type": "serial",
          "primaryKey": true,
          "notNull": true
        },
        "device_number": {
          "name": "device_number",
          "type": "varchar(255)",
          "primaryKey": false,
          "notNull": true
        },
        "phone_model": {
          "name": "phone_model",
          "type": "varchar(100)",
          "primaryKey": false,
          "notNull": false
        },
        "country_code": {
          "name": "country_code",
          "type": "varchar(10)",
          "primaryKey": false,
          "notNull": false
        },
        "version": {
          "name": "version",
          "type": "varchar(20)",
          "primaryKey": false,
          "notNull": false
        },
        "login_type": {
          "name": "login_type",
          "type": "integer",
          "primaryKey": false,
          "notNull": false,
          "default": 1
        },
        "created_at": {
          "name": "created_at",
          "type": "timestamp",
          "primaryKey": false,
          "notNull": false,
          "default": "now()"
        },
        "updated_at": {
          "name": "updated_at",
          "type": "timestamp",
          "primaryKey": false,
          "notNull": false,
          "default": "now()"
        }
      },
      "indexes": {},
      "foreignKeys": {},
      "compositePrimaryKeys": {},
      "uniqueConstraints": {
        "devices_device_number_unique": {
          "name": "devices_device_number_unique",
          "nullsNotDistinct": false,
          "columns": [
            "device_number"
          ]
        }
      },
      "policies": {},
      "checkConstraints": {},
      "isRLSEnabled": false
    },
    "public.users": {
      "name": "users",
      "schema": "",
      "columns": {
        "id": {
          "name": "id",
          "type": "serial",
          "primaryKey": true,
          "notNull": true
        },
        "username": {
          "name": "username",
          "type": "varchar(50)",
          "primaryKey": false,
          "notNull": true
        },
        "password": {
          "name": "password",
          "type": "varchar(255)",
          "primaryKey": false,
          "notNull": true
        },
        "email": {
          "name": "email",
          "type": "varchar(255)",
          "primaryKey": false,
          "notNull": true
        },
        "app_id": {
          "name": "app_id",
          "type": "integer",
          "primaryKey": false,
          "notNull": false
        },
        "created_at": {
          "name": "created_at",
          "type": "timestamp",
          "primaryKey": false,
          "notNull": false,
          "default": "now()"
        },
        "updated_at": {
          "name": "updated_at",
          "type": "timestamp",
          "primaryKey": false,
          "notNull": false,
          "default": "now()"
        }
      },
      "indexes": {},
      "foreignKeys": {
        "users_app_id_applications_id_fk": {
          "name": "users_app_id_applications_id_fk",
          "tableFrom": "users",
          "tableTo": "applications",
          "columnsFrom": [
            "app_id"
          ],
          "columnsTo": [
            "id"
          ],
          "onDelete": "no action",
          "onUpdate": "no action"
        }
      },
      "compositePrimaryKeys": {},
      "uniqueConstraints": {
        "users_username_unique": {
          "name": "users_username_unique",
          "nullsNotDistinct": false,
          "columns": [
            "username"
          ]
        },
        "users_email_unique": {
          "name": "users_email_unique",
          "nullsNotDistinct": false,
          "columns": [
            "email"
          ]
        }
      },
      "policies": {},
      "checkConstraints": {},
      "isRLSEnabled": false
    }
  },
  "enums": {},
  "schemas": {},
  "sequences": {},
  "roles": {},
  "policies": {},
  "views": {},
  "_meta": {
    "columns": {},
    "schemas": {},
    "tables": {}
  }
}